LICENSE
kada_ge_store_plugin/__init__.py
kada_ge_store_plugin/kada_store_validation.py
kada_ge_store_plugin-0.1.9.dist-info/METADATA
kada_ge_store_plugin-0.1.9.dist-info/WHEEL
kada_ge_store_plugin-0.1.9.dist-info/LICENSE
kada_ge_store_plugin-0.1.9.dist-info/RECORD
