Metadata-Version: 2.1
Name: kada-ge-store-plugin
Version: 0.1.9
Summary: Plugin package for great_expectations to store validation results in a different format in Azure storage.
Author: Ali Bhayani
Author-email: ali@cloudshuttle.com.au
Requires-Python: >=3.8,<4.0
Classifier: License :: OSI Approved :: MIT License
Classifier: Operating System :: OS Independent
Classifier: Programming Language :: Python :: 3
Classifier: Programming Language :: Python :: 3.8
Classifier: Programming Language :: Python :: 3.9
Classifier: Programming Language :: Python :: 3.10
Classifier: Programming Language :: Python :: 3.11
Classifier: Programming Language :: Python :: 3
Requires-Dist: azure-identity (==1.12.0)
Requires-Dist: azure-storage-blob (==12.14.1)
Project-URL: CloudShuttle, https://www.cloudshuttle.com.au/
